clocklock/__init__.py
clocklock/decorator.py
clocklock/timeoutter.py
clocklock-1.0.1.dist-info/LICENSE
clocklock-1.0.1.dist-info/METADATA
clocklock-1.0.1.dist-info/WHEEL
clocklock-1.0.1.dist-info/RECORD
