Metadata-Version: 2.1
Name: clocklock
Version: 1.0.1
Summary: A streamlined Python utility that enforces timeouts on your Python functions. It features a decorator and a function runner, both with provision for fallback functionality. Keep your code efficient and punctual, maintaining smooth control flow with ClockLock. Timing your Python functions has never been easier.
Author: Ram
Author-email: r4mbhardwaj@gmail.com
Requires-Python: >=3,<4
Classifier: Programming Language :: Python :: 3
Classifier: Programming Language :: Python :: 3.4
Classifier: Programming Language :: Python :: 3.5
Classifier: Programming Language :: Python :: 3.6
Classifier: Programming Language :: Python :: 3.7
Classifier: Programming Language :: Python :: 3.8
Classifier: Programming Language :: Python :: 3.9
Classifier: Programming Language :: Python :: 3.10
Classifier: Programming Language :: Python :: 3.11
Classifier: Programming Language :: Python :: 3.12
Requires-Dist: bumpversion (>=0.6.0,<0.7.0)
Requires-Dist: gitchangelog (>=3.0.4,<4.0.0)
